devdash/__init__.py
devdash/__main__.py
devdash/main.py
devdash/problems.json
devdashh-1.0.1.dist-info/licenses/LICENSE
devdashh-1.0.1.dist-info/METADATA
devdashh-1.0.1.dist-info/WHEEL
devdashh-1.0.1.dist-info/entry_points.txt
devdashh-1.0.1.dist-info/top_level.txt
devdashh-1.0.1.dist-info/RECORD
