Metadata-Version: 2.4
Name: devdashh
Version: 1.0.1
Summary: A terminal-based typing speed test for Python developers
Author: Neil Thomas
License-Expression: MIT
Project-URL: Homepage, https://github.com/neilthomass/devdashh
Project-URL: Repository, https://github.com/neilthomass/devdashh
Project-URL: Issues, https://github.com/neilthomass/devdashh/issues
Keywords: typing,speed-test,terminal,cli,python,leetcode,practice
Classifier: Development Status :: 4 - Beta
Classifier: Environment :: Console
Classifier: Intended Audience :: Developers
Classifier: Operating System :: MacOS
Classifier: Operating System :: POSIX :: Linux
Classifier: Programming Language :: Python :: 3
Classifier: Programming Language :: Python :: 3.8
Classifier: Programming Language :: Python :: 3.9
Classifier: Programming Language :: Python :: 3.10
Classifier: Programming Language :: Python :: 3.11
Classifier: Programming Language :: Python :: 3.12
Classifier: Topic :: Terminals
Classifier: Topic :: Education
Requires-Python: >=3.8
License-File: LICENSE
Dynamic: license-file
